nullaterra/__about__.py
nullaterra/__init__.py
nullaterra/arrays.py
nullaterra/bandpass_simulation.ipynb
nullaterra/constants.py
nullaterra/direction_of_arrival.py
nullaterra/filters.py
nullaterra/simulation.py
nullaterra/utils.py
nullaterra/weighting.py
nullaterra-0.0.1.dist-info/METADATA
nullaterra-0.0.1.dist-info/WHEEL
nullaterra-0.0.1.dist-info/licenses/LICENSE.txt
nullaterra-0.0.1.dist-info/RECORD
