Metadata-Version: 2.4
Name: nullaterra
Version: 0.0.1
Project-URL: Documentation, https://github.com/jdgsmallwood/nullaterra#readme
Project-URL: Issues, https://github.com/jdgsmallwood/nullaterra/issues
Project-URL: Source, https://github.com/jdgsmallwood/nullaterra
Author-email: Justin Smallwood <justin.d.smallwood@gmail.com>
License-Expression: MIT
License-File: LICENSE.txt
Classifier: Development Status :: 4 - Beta
Classifier: Programming Language :: Python
Classifier: Programming Language :: Python :: 3.8
Classifier: Programming Language :: Python :: 3.9
Classifier: Programming Language :: Python :: 3.10
Classifier: Programming Language :: Python :: 3.11
Classifier: Programming Language :: Python :: 3.12
Classifier: Programming Language :: Python :: Implementation :: CPython
Classifier: Programming Language :: Python :: Implementation :: PyPy
Requires-Python: >=3.8
Requires-Dist: astropy
Requires-Dist: black
Requires-Dist: fastexcel
Requires-Dist: hypothesis
Requires-Dist: isort
Requires-Dist: jupyterlab
Requires-Dist: loguru
Requires-Dist: matplotlib
Requires-Dist: numpy
Requires-Dist: openpyxl
Requires-Dist: plotly
Requires-Dist: polars
Requires-Dist: pytest
Requires-Dist: ruff
Requires-Dist: scipy
Requires-Dist: skyfield
Requires-Dist: streamlit
Requires-Dist: tqdm
Requires-Dist: xlsxwriter
